{
    "name": "host_io",
    "version": "1.0.0",
    "label": "host.io",
    "description": "Get comprehensive domain name data, uncover new domains and the relationships between them. Also get DNS details, scraped website content, outbound links, backlinks, and other hosting details for any domain.",
    "publisher": "spryIQ.co",
    "icon_small_name": "host_io32x32.png",
    "icon_large_name": "host_io100x100.png",
    "help_online": "",
    "category": "Cyber Security",
    "cs_compatible": true,
    "cs_approved": false,
    "configuration": {
        "fields": [
            {
                "title": "API Token",
                "type": "text",
                "description": "Provide API token, used for user authentication.",
                "tooltip": "Provide API token, used for user authentication.",
                "name": "token",
                "required": true,
                "visible": true,
                "editable": true,
                "value": ""
            },
            {
                "title": "Server URL",
                "type": "text",
                "description": "URL of the host.io connector to access the connector website.",
                "tooltip": "URL of the host.io connector to access the connector website. e.g, https://host.io",
                "value": "host.io",
                "placeholder": "host.io",
                "name": "server",
                "required": true,
                "visible": true,
                "editable": true
            }
        ]
    },
    "operations": [
        {
            "operation": "web_domain",
            "title": "Web Domain",
            "description": "Metadata scraped from a domain homepage.",
            "enabled": true,
            "category": "investigation",
            "annotation": "web_domain",
            "output_schema": {
                "domain": "",
                "rank": "",
                "url": "",
                "ip": "",
                "date": "",
                "length": "",
                "encoding": "",
                "copyright": "",
                "title": "",
                "description": "",
                "links": []
            },
            "parameters": [
                {
                    "title": "Endpoint URL",
                    "type": "text",
                    "name": "endpoint_url",
                    "required": true,
                    "visible": true,
                    "editable": true,
                    "value": "",
                    "placeholder": "facebook.com",
                    "description": "Endpoint URL name for which you want to retrieve a host.io list of domains.",
                    "tooltip": "Endpoint URL name for which you want to retrieve a host.io list of domains."
                }
            ]
        },
        {
            "operation": "dns_domain",
            "title": "DNS Domain",
            "description": "Get all the DNS records stored for a domain.",
            "enabled": true,
            "category": "investigation",
            "annotation": "dns_domain",
            "output_schema": {
                "domain": "",
                "a": [],
                "aaaa": [],
                "mx": [],
                "ns": []
            },
            "parameters": [
                {
                    "title": "Endpoint URL",
                    "type": "text",
                    "name": "endpoint_url",
                    "required": true,
                    "visible": true,
                    "editable": true,
                    "value": "",
                    "placeholder": "facebook.com",
                    "description": "Endpoint URL name for which you want to retrieve a host.io list of domains.",
                    "tooltip": "Endpoint URL name for which you want to retrieve a host.io list of domains."
                }
            ]
        },
        {
            "operation": "related_domain",
            "title": "Related Domain",
            "description": "Get a count of the number of related domains for all supported lookups offered by host.io.",
            "enabled": true,
            "category": "investigation",
            "annotation": "related_domain",
            "output_schema": {
                "ip": [],
                "redirects": [],
                "backlinks": [],
                "asn": []
            },
            "parameters": [
                {
                    "title": "Endpoint URL",
                    "type": "text",
                    "name": "endpoint_url",
                    "required": true,
                    "visible": true,
                    "editable": true,
                    "value": "",
                    "placeholder": "google.com",
                    "description": "Endpoint URL name for which you want to retrieve a host.io list of domains.",
                    "tooltip": "Endpoint URL name for which you want to retrieve a host.io list of domains."
                }
            ]
        },
        {
            "operation": "get_full_domains_data",
            "title": "Full Domains",
            "description": "A single endpoint that includes the data from WEB DOMAIN, DNS DOMAIN, RELATED DOMAIN and IPinfo.",
            "enabled": true,
            "category": "investigation",
            "annotation": "get_full_domains_data",
            "output_schema": {
                "domain": "",
                "dns": {},
                "ipinfo": {},
                "web": {},
                "related": {}
            },
            "parameters": [
                {
                    "title": "Endpoint URL",
                    "type": "text",
                    "name": "endpoint_url",
                    "required": true,
                    "visible": true,
                    "editable": true,
                    "value": "",
                    "placeholder": "google.com",
                    "description": "Endpoint URL name for which you want to retrieve a host.io list of domains.",
                    "tooltip": "Endpoint URL name for which you want to retrieve a host.io list of domains."
                }
            ]
        },
        {
            "operation": "get_all_domains",
            "title": "Get all Domains",
            "description": "Get all domains associated with :field, and a count of the total. The :value should be according to the :field and not necessarily a domain.",
            "enabled": true,
            "category": "investigation",
            "annotation": "get_all_domains",
            "output_schema": {
                "total": 0,
                "domains": []
            },
            "parameters": [
                {
                    "title": "Field",
                    "type": "text",
                    "name": "field",
                    "required": true,
                    "visible": true,
                    "editable": true,
                    "value": "",
                    "placeholder": "googleanalytics",
                    "description": "Provide field name to get associated domains.",
                    "tooltip": "Provide field name to get associated domains."
                },
                {
                    "title": "Value",
                    "type": "text",
                    "name": "value",
                    "required": true,
                    "visible": true,
                    "editable": true,
                    "value": "",
                    "placeholder": "UA-61330992",
                    "description": "The value should be according to the field and not necessarily a domain.",
                    "tooltip": "The value should be according to the field and not necessarily a domain."
                },
                {
                    "title": "Limit",
                    "type": "integer",
                    "name": "limit",
                    "required": false,
                    "visible": true,
                    "editable": true,
                    "value": 25,
                    "description": "Must be one of 0, 1, 5, 10, 25, 100, 250, or 1000. Default is 25.",
                    "tooltip": "Must be one of 0, 1, 5, 10, 25, 100, 250, or 1000. Default is 25."
                },
                {
                    "title": "Page",
                    "type": "integer",
                    "name": "page",
                    "required": false,
                    "visible": true,
                    "editable": true,
                    "value": 0,
                    "description": "The page of data to view, 0-indexed. Default is 0. Pagination takes into account the limit.",
                    "tooltip": "The page of data to view, 0-indexed. Default is 0. Pagination takes into account the limit."
                }
            ]
        }
    ]
}